clarity/__init__.py
clarity/clarity.py
clarity/hud.py
lol_clarity-0.3.0.dist-info/DESCRIPTION.rst
lol_clarity-0.3.0.dist-info/METADATA
lol_clarity-0.3.0.dist-info/metadata.json
lol_clarity-0.3.0.dist-info/RECORD
lol_clarity-0.3.0.dist-info/top_level.txt
lol_clarity-0.3.0.dist-info/WHEEL
